multivoro/__init__.py
multivoro/exceptions.py
multivoro/_multivoro.cpython-39-darwin.so
multivoro-0.1.2.dist-info/RECORD
multivoro-0.1.2.dist-info/WHEEL
multivoro-0.1.2.dist-info/METADATA
multivoro-0.1.2.dist-info/licenses/LICENSE
