Metadata-Version: 2.1
Name: multivoro
Version: 0.1.2
Summary: Parallel cell-based 3D voronoi tessellations
Author-Email: Eleftherios Zisis <elef.zisis@gmail.com>
Classifier: Development Status :: 3 - Alpha
Classifier: Intended Audience :: Developers
Classifier: Intended Audience :: Science/Research
Classifier: Programming Language :: Python :: 3
Classifier: Programming Language :: Python :: 3.8
Classifier: Programming Language :: Python :: 3.9
Classifier: Programming Language :: Python :: 3.10
Classifier: Programming Language :: Python :: 3.11
Classifier: Programming Language :: Python :: 3.12
Classifier: Programming Language :: Python :: 3.13
Classifier: Programming Language :: Python :: 3.14
Classifier: Topic :: Scientific/Engineering :: Mathematics
Project-URL: Homepage, https://github.com/eleftherioszisis/multivoro
Requires-Python: >=3.8
Requires-Dist: numpy
